celery_heimdall/__init__.py
celery_heimdall/config.py
celery_heimdall/contrib/README.md
celery_heimdall/contrib/__init__.py
celery_heimdall/contrib/inspector/README.md
celery_heimdall/contrib/inspector/__init__.py
celery_heimdall/contrib/inspector/cli.py
celery_heimdall/contrib/inspector/models.py
celery_heimdall/contrib/inspector/monitor.py
celery_heimdall/errors.py
celery_heimdall/task.py
celery_heimdall-1.0.1.dist-info/LICENSE
celery_heimdall-1.0.1.dist-info/METADATA
celery_heimdall-1.0.1.dist-info/WHEEL
celery_heimdall-1.0.1.dist-info/entry_points.txt
celery_heimdall-1.0.1.dist-info/RECORD
