Metadata-Version: 2.1
Name: celery-heimdall
Version: 1.0.1
Summary: Helpful celery extensions.
Home-page: https://github.com/tktech/celery-heimdall
License: MIT
Author: Tyler Kennedy
Author-email: tk@tkte.ch
Requires-Python: >=3.8,<4.0
Classifier: License :: OSI Approved :: MIT License
Classifier: Programming Language :: Python :: 3
Classifier: Programming Language :: Python :: 3.8
Classifier: Programming Language :: Python :: 3.9
Classifier: Programming Language :: Python :: 3.10
Classifier: Programming Language :: Python :: 3.11
Classifier: Programming Language :: Python :: 3.12
Provides-Extra: inspector
Requires-Dist: SQLAlchemy ; extra == "inspector"
Requires-Dist: celery
Requires-Dist: click ; extra == "inspector"
Requires-Dist: redis
Project-URL: Repository, https://github.com/tktech/celery-heimdall
